senml/__init__.py
senml/senml.py
senml-0.1.0.dist-info/DESCRIPTION.rst
senml-0.1.0.dist-info/METADATA
senml-0.1.0.dist-info/RECORD
senml-0.1.0.dist-info/WHEEL
senml-0.1.0.dist-info/metadata.json
senml-0.1.0.dist-info/top_level.txt
