Metadata-Version: 2.0
Name: senml
Version: 0.1.0
Summary: SenML library
Home-page: https://github.com/eistec/senml-python/
Author: Joakim Nohlgård
Author-email: joakim.nohlgard@eistec.se
License: Apache Software License
Download-URL: https://github.com/eistec/senml-python/archive/v0.1.0.tar.gz
Keywords: senml,iot
Platform: any
Classifier: Programming Language :: Python :: 3.4
Classifier: Programming Language :: Python :: 3.5
Classifier: Development Status :: 3 - Alpha
Classifier: Environment :: Web Environment
Classifier: Intended Audience :: Developers
Classifier: Intended Audience :: Science/Research
Classifier: License :: OSI Approved :: Apache Software License
Classifier: Operating System :: OS Independent
Classifier: Topic :: Software Development :: Libraries :: Python Modules
Classifier: Topic :: Internet :: WWW/HTTP :: Dynamic Content
Classifier: Topic :: Internet
Classifier: Topic :: Home Automation
Classifier: Topic :: Scientific/Engineering :: Interface Engine/Protocol Translator
Requires-Dist: attrs (>=16.0.0)
Requires-Dist: cbor (>=1.0.0)
Provides-Extra: testing
Requires-Dist: cov; extra == 'testing'
Requires-Dist: pylint; extra == 'testing'
Requires-Dist: pytest; extra == 'testing'
